[
  {"id":1,"title":"Планиметрия","short":"Фигуры на плоскости"},
  {"id":2,"title":"Векторы","short":"Координаты и векторы"},
  {"id":3,"title":"Стереометрия","short":"Фигуры в пространстве"},
  {"id":4,"title":"Простая вероятность","short":"Одно случайное событие"},
  {"id":5,"title":"Сложная вероятность","short":"Несколько событий"},
  {"id":6,"title":"Уравнения","short":"Простейшие уравнения"},
  {"id":7,"title":"Вычисления","short":"Преобразования и значения"},
  {"id":8,"title":"Производная и первообразная","short":"Чтение графиков"},
  {"id":9,"title":"Прикладная математика","short":"Формулы и зависимости"},
  {"id":10,"title":"Текстовые задачи","short":"Движение, работа, проценты"},
  {"id":11,"title":"Функции и графики","short":"Свойства функций"},
  {"id":12,"title":"Наибольшее и наименьшее","short":"Экстремумы функций"},
  {"id":13,"title":"Уравнения с развёрнутым ответом","short":"Тригонометрические и смешанные уравнения"},
  {"id":14,"title":"Стереометрия с доказательством","short":"Геометрия в пространстве"},
  {"id":15,"title":"Неравенства","short":"Рациональные, показательные и логарифмические"},
  {"id":16,"title":"Планиметрия с доказательством","short":"Геометрия на плоскости"},
  {"id":17,"title":"Финансовая математика","short":"Кредиты, вклады и экономические модели"},
  {"id":18,"title":"Задачи с параметром","short":"Уравнения и неравенства с параметрами"},
  {"id":19,"title":"Числа и их свойства","short":"Делимость и целочисленные конструкции"}
]
